matrice_dataset/__init__.py
matrice_dataset/aug_server.py
matrice_dataset/aug_server_v2.py
matrice_dataset/client.py
matrice_dataset/client_utils.py
matrice_dataset/create_dataset.py
matrice_dataset/data_augmentation.py
matrice_dataset/data_augmentor.py
matrice_dataset/data_generation.py
matrice_dataset/data_generator.py
matrice_dataset/data_labelling.py
matrice_dataset/data_prep.py
matrice_dataset/data_processor.py
matrice_dataset/image_augmentations.py
matrice_dataset/image_data_augmentation.py
matrice_dataset/new_data_augmentation.py
matrice_dataset/pipeline.py
matrice_dataset/py.typed
matrice_dataset/server.py
matrice_dataset/server_utils.py
matrice_dataset/video_server.py
matrice_dataset/augmentation_utils/__init__.py
matrice_dataset/augmentation_utils/base.py
matrice_dataset/augmentation_utils/strategies/__init__.py
matrice_dataset/augmentation_utils/strategies/bit_depth_reduction.py
matrice_dataset/augmentation_utils/strategies/blur.py
matrice_dataset/augmentation_utils/strategies/brightness_contrast.py
matrice_dataset/augmentation_utils/strategies/color_jitter.py
matrice_dataset/augmentation_utils/strategies/compression_artifacts.py
matrice_dataset/augmentation_utils/strategies/downscale_upscale.py
matrice_dataset/augmentation_utils/strategies/film_grain.py
matrice_dataset/augmentation_utils/strategies/flip.py
matrice_dataset/augmentation_utils/strategies/fog.py
matrice_dataset/augmentation_utils/strategies/horizontal_flip.py
matrice_dataset/augmentation_utils/strategies/hsv.py
matrice_dataset/augmentation_utils/strategies/iso_noise.py
matrice_dataset/augmentation_utils/strategies/low_light.py
matrice_dataset/augmentation_utils/strategies/posterize.py
matrice_dataset/augmentation_utils/strategies/rain.py
matrice_dataset/augmentation_utils/strategies/random_affine.py
matrice_dataset/augmentation_utils/strategies/salt_pepper.py
matrice_dataset/augmentation_utils/strategies/shadows.py
matrice_dataset/augmentation_utils/strategies/snow.py
matrice_dataset-0.1.1.dist-info/licenses/LICENSE.txt
matrice_dataset-0.1.1.dist-info/METADATA
matrice_dataset-0.1.1.dist-info/WHEEL
matrice_dataset-0.1.1.dist-info/top_level.txt
matrice_dataset-0.1.1.dist-info/RECORD
